lavague/drivers/driverserver/__init__.py
lavague/drivers/driverserver/base.py
lavague_drivers_remote-0.2.5.dist-info/METADATA
lavague_drivers_remote-0.2.5.dist-info/WHEEL
lavague_drivers_remote-0.2.5.dist-info/RECORD
