Metadata-Version: 2.1
Name: lavague-drivers-remote
Version: 0.2.5
Summary: Remote driver execution for Lavague
Home-page: https://lavague.ai
License: Apache-2.0
Keywords: LAM,action,automation,LLM,NLP,RAG,selenium,selenium
Author: lavague-ai
Requires-Python: >=3.10.0,<4.0.0
Classifier: Development Status :: 3 - Alpha
Classifier: Intended Audience :: Developers
Classifier: License :: OSI Approved :: Apache Software License
Classifier: Programming Language :: Python :: 3
Classifier: Programming Language :: Python :: 3.10
Classifier: Programming Language :: Python :: 3.11
Classifier: Programming Language :: Python :: 3.12
Classifier: Topic :: Scientific/Engineering :: Artificial Intelligence
Classifier: Topic :: Software Development :: Libraries :: Application Frameworks
Classifier: Topic :: Software Development :: Libraries :: Python Modules
Requires-Dist: lavague-core (>=0.2.0,<0.3.0)
Requires-Dist: lavague-server (>=0.0.3,<0.0.4)
Requires-Dist: websockets (>=11.0,<12.0)
Project-URL: Documentation, https://docs.lavague.ai/en/latest/
Project-URL: Repository, https://github.com/lavague-ai/LaVague/
